isotopylog/__init__.py
isotopylog/calc_funcs.py
isotopylog/core_functions.py
isotopylog/dictionaries.py
isotopylog/ratedata.py
isotopylog/ratedata_helper.py
isotopylog/timedata.py
isotopylog/timedata_helper.py
isotopylog/lit_values/lit_values.csv
isotopylog-0.0.8.dist-info/METADATA
isotopylog-0.0.8.dist-info/WHEEL
isotopylog-0.0.8.dist-info/top_level.txt
isotopylog-0.0.8.dist-info/RECORD
