Metadata-Version: 2.1
Name: isotopylog
Version: 0.0.8
Summary: Clumped isotope kinetic analysis
Home-page: https://github.com/FluvialSeds/isotopylog
Download-URL: https://github.com/FluvialSeds/isotopylog/tarball/0.0.8
Author: Jordon D. Hemingway
Author-email: jordon.hemingway@erdw.ethz.ch
License: GNU GPL Version 3
Keywords: geochemistry,clumped isotopes,kinetics,inverse modeling,carbon cycle
Classifier: Development Status :: 3 - Alpha
Classifier: Intended Audience :: Science/Research
Classifier: License :: Free for non-commercial use
Classifier: Programming Language :: Python
Classifier: Programming Language :: Python :: 3
Classifier: Programming Language :: Python :: 2
Classifier: Programming Language :: Python :: 3.5
Classifier: Programming Language :: Python :: 2.7
Classifier: Topic :: Scientific/Engineering
